llmo-0.5.1.dist-info/METADATA
llmo-0.5.1.dist-info/WHEEL
llmo-0.5.1.dist-info/entry_points.txt
llmo-0.5.1.dist-info/licenses/LICENSE
llmo/__init__.py
llmo/cli.py
llmo/constants.py
llmo/gui.py
llmo/layout.css
llmo/llms.py
llmo/shell_mode.py
llmo-0.5.1.dist-info/RECORD
