Metadata-Version: 2.1
Name: llmo
Version: 0.5.1
Summary: AI pair programmer
Author-Email: Stephan Fitzpatrick <stephan@knowsuchagency.com>
License: Apache-2.0
Project-URL: Source, https://github.com/knowsuchagency/llmo
Requires-Python: >=3.10
Requires-Dist: textual>=0.26.0
Requires-Dist: openai>=0.27.6
Requires-Dist: tenacity>=8.2.2
